{
  "project_info": {
    "project_number": "261526967611",
    "firebase_url": "https://dalrat.firebaseio.com",
    "project_id": "dalrat",
    "storage_bucket": "dalrat.appspot.com"
  },
  "client": [
    {
      "client_info": {
        "mobilesdk_app_id": "1:261526967611:android:bdec33a2644eae37ef531e",
        "android_client_info": {
          "package_name": "com.and.dalrat"
        }
      },
      "oauth_client": [
        {
          "client_id": "261526967611-a0uf907kdsdbvmfv42n6u8edp5844inh.apps.googleusercontent.com",
          "client_type": 1,
          "android_info": {
            "package_name": "com.and.dalrat",
            "certificate_hash": "77fd710a50cbcd17e4122fefd2de6a53094db17e"
          }
        },
        {
          "client_id": "261526967611-dbbs04vcrqfgg43ot1sqmp2qio3dt2d7.apps.googleusercontent.com",
          "client_type": 3
        }
      ],
      "api_key": [
        {
          "current_key": "AIzaSyDLlRxNuOxfk8Kbc6sz1DS3e810eH0zwPw"
        }
      ],
      "services": {
        "appinvite_service": {
          "other_platform_oauth_client": [
            {
              "client_id": "261526967611-dbbs04vcrqfgg43ot1sqmp2qio3dt2d7.apps.googleusercontent.com",
              "client_type": 3
            }
          ]
        }
      }
    }
  ],
  "configuration_version": "1"
}
